mx_remote/Interface.py
mx_remote/Uid.py
mx_remote/__init__.py
mx_remote/const.py
mx_remote/main.py
mx_remote/api/BayConfig.py
mx_remote/api/__init__.py
mx_remote/proto/BayConfig.py
mx_remote/proto/Constants.py
mx_remote/proto/Data.py
mx_remote/proto/Factory.py
mx_remote/proto/FrameAmpDolbySettings.py
mx_remote/proto/FrameAmpZoneSettings.py
mx_remote/proto/FrameBase.py
mx_remote/proto/FrameBayConfig.py
mx_remote/proto/FrameBayConfigSecondary.py
mx_remote/proto/FrameBayHide.py
mx_remote/proto/FrameBayStatus.py
mx_remote/proto/FrameConnectStatus.py
mx_remote/proto/FrameDiscover.py
mx_remote/proto/FrameEDID.py
mx_remote/proto/FrameEDIDProfile.py
mx_remote/proto/FrameFilterStatus.py
mx_remote/proto/FrameFirmwareVersion.py
mx_remote/proto/FrameHeader.py
mx_remote/proto/FrameHello.py
mx_remote/proto/FrameLinks.py
mx_remote/proto/FrameMeshOperation.py
mx_remote/proto/FrameMirrorStatus.py
mx_remote/proto/FrameNetworkStatus.py
mx_remote/proto/FramePDUState.py
mx_remote/proto/FramePowerChange.py
mx_remote/proto/FrameRCAction.py
mx_remote/proto/FrameRCIr.py
mx_remote/proto/FrameRCKey.py
mx_remote/proto/FrameReboot.py
mx_remote/proto/FrameRoutingChange.py
mx_remote/proto/FrameSetName.py
mx_remote/proto/FrameSignalStatus.py
mx_remote/proto/FrameSignalStatusNew.py
mx_remote/proto/FrameSysTemperature.py
mx_remote/proto/FrameTXRCAction.py
mx_remote/proto/FrameTopology.py
mx_remote/proto/FrameV2IPDeviceConfiguration.py
mx_remote/proto/FrameV2IPLink.py
mx_remote/proto/FrameV2IPSetMaster.py
mx_remote/proto/FrameV2IPSourceSwitch.py
mx_remote/proto/FrameV2IPSources.py
mx_remote/proto/FrameV2IPStats.py
mx_remote/proto/FrameV2IPStreamDetails.py
mx_remote/proto/FrameVolume.py
mx_remote/proto/FrameVolumeDown.py
mx_remote/proto/FrameVolumeSet.py
mx_remote/proto/FrameVolumeUp.py
mx_remote/proto/LinkConfig.py
mx_remote/proto/PDUState.py
mx_remote/proto/Svd.py
mx_remote/proto/V2IPConfig.py
mx_remote/proto/V2IPStats.py
mx_remote/proto/__init__.py
mx_remote/proto/svd.csv
mx_remote/remote/Bay.py
mx_remote-2.0.0.dist-info/METADATA
mx_remote-2.0.0.dist-info/WHEEL
mx_remote-2.0.0.dist-info/entry_points.txt
mx_remote-2.0.0.dist-info/licenses/LICENSE
mx_remote-2.0.0.dist-info/RECORD
