Metadata-Version: 2.3
Name: mx_remote
Version: 2.0.0
Summary: Python 3 library for interfacing with MX Remote compatible devices
Project-URL: Homepage, https://github.com/opdenkamp/mx-remote/
Project-URL: Documentation, https://github.com/opdenkamp/mx-remote/
Project-URL: Repository, https://github.com/opdenkamp/mx-remote.git
Project-URL: Bug Tracker, https://github.com/opdenkamp/mx-remote/issues
Author-email: Lars Op den Kamp <lars@opdenkamp.eu>
Maintainer-email: Lars Op den Kamp <lars@opdenkamp.eu>
License: Copyright 2024 Lars Op den Kamp <lars@opdenkamp.eu>
Keywords: ampos,matrixos,oneip,pulse-eight
Classifier: Development Status :: 3 - Alpha
Classifier: Programming Language :: Python
Classifier: Topic :: System :: Networking :: Monitoring
Requires-Python: >=3.11
Requires-Dist: aiofiles>=24.1.0
Requires-Dist: aiohttp>=3.10.5
Requires-Dist: argparse>=1.4.0
Requires-Dist: netifaces>=0.11.0
